aidsorb/__init__.py
aidsorb/_cli.py
aidsorb/_internal.py
aidsorb/_torch_utils.py
aidsorb/_transforms_utils.py
aidsorb/data.py
aidsorb/datamodules.py
aidsorb/litmodules.py
aidsorb/modules.py
aidsorb/transforms.py
aidsorb/utils.py
aidsorb/visualize.py
aidsorb/pkg_data/README.md
aidsorb/pkg_data/periodic_table.csv
aidsorb-2.0.0.dist-info/licenses/LICENSE
aidsorb-2.0.0.dist-info/METADATA
aidsorb-2.0.0.dist-info/WHEEL
aidsorb-2.0.0.dist-info/entry_points.txt
aidsorb-2.0.0.dist-info/top_level.txt
aidsorb-2.0.0.dist-info/RECORD
