Metadata-Version: 2.4
Name: aidsorb
Version: 2.0.0
Summary: Python package for deep learning on molecular point clouds.
Author-email: "Antonios P. Sarikas" <antonios.sarikas@gmail.com>
License-Expression: GPL-3.0-only
Project-URL: Homepage, https://github.com/adosar/aidsorb
Project-URL: Issues, https://github.com/adosar/aidsorb/issues
Project-URL: Documentation, https://aidsorb.readthedocs.io/en/stable/
Classifier: Programming Language :: Python :: 3
Classifier: Operating System :: POSIX :: Linux
Requires-Python: >=3.11
License-File: LICENSE
Requires-Dist: ase>=3.23.0
Requires-Dist: plotly>=5.19.0
Requires-Dist: tqdm>=4.66.2
Requires-Dist: pandas>=2.2.0
Requires-Dist: roma>=1.5.1
Requires-Dist: lightning>=2.5.0
Requires-Dist: jsonargparse[signatures]>=4.39.0
Requires-Dist: torchmetrics>=1.7.1
Requires-Dist: numpy>=1.26.4
Provides-Extra: docs
Requires-Dist: sphinx>=8.2.3; extra == "docs"
Requires-Dist: sphinx-rtd-theme==3.0.2; extra == "docs"
Requires-Dist: sphinx-copybutton>=0.5.2; extra == "docs"
Requires-Dist: sphinx-design>=0.6.1; extra == "docs"
Requires-Dist: sphinx-gallery>=0.16.0; extra == "docs"
Requires-Dist: kaleido==0.2.1; extra == "docs"
Dynamic: license-file
